colorbundle/__init__.py
colorbundle/templatetags/__init__.py
colorbundle/templatetags/colorbundle_tags.py
django_colorbundle-0.1.2.dist-info/DESCRIPTION.rst
django_colorbundle-0.1.2.dist-info/METADATA
django_colorbundle-0.1.2.dist-info/RECORD
django_colorbundle-0.1.2.dist-info/WHEEL
django_colorbundle-0.1.2.dist-info/metadata.json
django_colorbundle-0.1.2.dist-info/top_level.txt
